rtl/alu.sv
module alu(
    input  logic [31:0] a,
    input  logic [31:0] b,
    input  logic [3:0]  alu_ctrl,
    output logic [31:0] result,
    output logic        zero
);

always_comb begin
    case (alu_ctrl)
        4'b0000: result = a + b;                       // ADD
        4'b0001: result = a - b;                       // SUB
        4'b0010: result = a & b;                       // AND
        4'b0011: result = a | b;                       // OR
        4'b0100: result = a ^ b;                       // XOR
        4'b0101: result = a << b[4:0];                 // SLL
        4'b0110: result = a >> b[4:0];                 // SRL
        4'b0111: result = $signed(a) >>> b[4:0];       // SRA
        4'b1000: result = ($signed(a) < $signed(b));   // SLT
        default: result = 32'b0;
    endcase
end

assign zero = (result == 0);

endmodule

tb/alu_tb.sv
`timescale 1ns/1ps

module alu_tb;

logic [31:0] a, b;
logic [3:0] alu_ctrl;
logic [31:0] result;
logic zero;

alu dut (
    .a(a),
    .b(b),
    .alu_ctrl(alu_ctrl),
    .result(result),
    .zero(zero)
);

initial begin
    $dumpfile("wave.vcd");
    $dumpvars(0, alu_tb);

    // ADD
    a = 10; b = 5; alu_ctrl = 4'b0000;
    #10;
    if (result !== 32'd15) $error("ADD failed: got %0d", result);

    // SUB
    alu_ctrl = 4'b0001;
    #10;
    if (result !== 32'd5) $error("SUB failed: got %0d", result);

    // AND
    alu_ctrl = 4'b0010;
    #10;
    if (result !== 32'd0) $error("AND failed: got %0d", result);

    // OR
    alu_ctrl = 4'b0011;
    #10;
    if (result !== 32'd15) $error("OR failed: got %0d", result);

    // SLT
    a = -1; b = 1; alu_ctrl = 4'b1000;
    #10;
    if (result !== 32'd1) $error("SLT failed: got %0d", result);

        // XOR
    a = 32'hF0F0F0F0; b = 32'h0FF00FF0; alu_ctrl = 4'b0100;
    #10;
    if (result !== 32'hFF00FF00) $error("XOR failed: got %h", result);

    // SLL
    a = 32'd1; b = 32'd4; alu_ctrl = 4'b0101;
    #10;
    if (result !== 32'd16) $error("SLL failed: got %0d", result);

    // SRL
    a = 32'd16; b = 32'd2; alu_ctrl = 4'b0110;
    #10;
    if (result !== 32'd4) $error("SRL failed: got %0d", result);

    // SRA
    a = -32'd8; b = 32'd1; alu_ctrl = 4'b0111;
    #10;
    if (result !== -32'd4) $error("SRA failed: got %0d", result);

    // zero flag after subtraction
    a = 32'd9; b = 32'd9; alu_ctrl = 4'b0001;
    #10;
    if (result !== 32'd0) $error("Zero-result SUB failed: got %0d", result);
    if (zero !== 1'b1) $error("Zero flag failed: got %b", zero);

    $display("All ALU tests passed.");
    $finish;
end

endmodule

wave.vcd
$date
	Sun Mar  8 20:53:45 2026
$end
$version
	Icarus Verilog
$end
$timescale
	1ps
$end
$scope module alu_tb $end
$var wire 1 ! zero $end
$var wire 32 " result [31:0] $end
$var reg 32 # a [31:0] $end
$var reg 4 $ alu_ctrl [3:0] $end
$var reg 32 % b [31:0] $end
$scope module dut $end
$var wire 32 & a [31:0] $end
$var wire 4 ' alu_ctrl [3:0] $end
$var wire 32 ( b [31:0] $end
$var wire 1 ! zero $end
$var reg 32 ) result [31:0] $end
$upscope $end
$upscope $end
$enddefinitions $end
$comment Show the parameter values. $end
$dumpall
$end
#0
$dumpvars
b1111 )
b101 (
b0 '
b1010 &
b101 %
b0 $
b1010 #
b1111 "
0!
$end
#10000
b101 "
b101 )
b1 $
b1 '
#20000
1!
b0 "
b0 )
b10 $
b10 '
#30000
0!
b1111 "
b1111 )
b11 $
b11 '
#40000
b1 "
b1 )
b1000 $
b1000 '
b1 %
b1 (
b11111111111111111111111111111111 #
b11111111111111111111111111111111 &
#50000
b11111111000000001111111100000000 "
b11111111000000001111111100000000 )
b100 $
b100 '
b1111111100000000111111110000 %
b1111111100000000111111110000 (
b11110000111100001111000011110000 #
b11110000111100001111000011110000 &
#60000
b10000 "
b10000 )
b101 $
b101 '
b100 %
b100 (
b1 #
b1 &
#70000
b100 "
b100 )
b110 $
b110 '
b10 %
b10 (
b10000 #
b10000 &
#80000
b11111111111111111111111111111100 "
b11111111111111111111111111111100 )
b111 $
b111 '
b1 %
b1 (
b11111111111111111111111111111000 #
b11111111111111111111111111111000 &
#90000
1!
b0 "
b0 )
b1 $
b1 '
b1001 %
b1001 (
b1001 #
b1001 &
